{
  "2025-11-19": {
    "early": {
      "name": "Alexandra Hock",
      "email": "alexandra.hock@ringcentral.com",
      "schedule": {
        "sun": "OFF",
        "mon": "05:00-14:00",
        "tue": "05:00-14:00",
        "wed": "05:00-14:00",
        "thu": "05:00-14:00",
        "fri": "05:00-14:00",
        "sat": "OFF"
      },
      "shift": "early"
    },
    "day": {
      "name": "Rochelle Gobis",
      "email": "rochelle.gobis@ringcentral.com",
      "schedule": {
        "sun": "OFF",
        "mon": "08:00-15:30",
        "tue": "08:00-15:30",
        "wed": "08:00-15:30",
        "thu": "08:00-15:30",
        "fri": "08:00-15:30",
        "sat": "OFF"
      },
      "shift": "day"
    },
    "evening": {
      "name": "Lara Mae Dela Cruz",
      "email": "lara.delacruz@ringcentral.com",
      "schedule": {
        "sun": "OFF",
        "mon": "15:00-00:00",
        "tue": "15:00-00:00",
        "wed": "15:00-00:00",
        "thu": "15:00-00:00",
        "fri": "15:00-00:00",
        "sat": "OFF"
      },
      "shift": "evening"
    },
    "night": {
      "name": "Rushikesh Sawant",
      "email": "rushikesh.sawant@ringcentral.com",
      "schedule": {
        "sun": "22:30-07:30",
        "mon": "22:30-07:30",
        "tue": "22:30-07:30",
        "wed": "22:30-07:30",
        "thu": "22:30-07:30",
        "fri": "OFF",
        "sat": "OFF"
      },
      "shift": "night"
    }
  },
  "2025-11-20": {
    "early": {
      "name": "Marina Stambaugh",
      "email": "marina.stambaugh@ringcentral.com",
      "schedule": {
        "sun": "OFF",
        "mon": "07:00-16:00",
        "tue": "07:00-16:00",
        "wed": "07:00-16:00",
        "thu": "07:00-16:00",
        "fri": "07:00-16:00",
        "sat": "OFF"
      },
      "shift": "early"
    },
    "day": {
      "name": "Sarah Heriford",
      "email": "sarah.heriford@ringcentral.com",
      "schedule": {
        "sun": "OFF",
        "mon": "08:00-16:30",
        "tue": "08:00-16:30",
        "wed": "08:00-16:30",
        "thu": "08:00-16:30",
        "fri": "08:00-16:30",
        "sat": "OFF"
      },
      "shift": "day"
    },
    "evening": {
      "name": "Love Lyn Cano",
      "email": "love.cano@ringcentral.com",
      "schedule": {
        "sun": "15:00-00:00",
        "mon": "15:00-00:00",
        "tue": "15:00-00:00",
        "wed": "15:00-00:00",
        "thu": "OFF",
        "fri": "OFF",
        "sat": "15:00-00:00"
      },
      "shift": "evening"
    },
    "night": {
      "name": "Santosh Sahoo",
      "email": "santosh.sahoo@ringcentral.com",
      "schedule": {
        "sun": "22:30-07:30",
        "mon": "22:30-07:30",
        "tue": "22:30-07:30",
        "wed": "22:30-07:30",
        "thu": "22:30-07:30",
        "fri": "OFF",
        "sat": "OFF"
      },
      "shift": "night"
    }
  },
  "2025-11-21": {
    "early": {
      "name": "Jenny Deasy",
      "email": "jenny.deasy@ringcentral.com",
      "schedule": {
        "sun": "OFF",
        "mon": "07:00-15:30",
        "tue": "07:00-15:30",
        "wed": "07:00-15:30",
        "thu": "07:00-15:30",
        "fri": "07:00-15:30",
        "sat": "OFF"
      },
      "shift": "early"
    },
    "day": {
      "name": "Karla Talamantes",
      "email": "karla.talamantes@ringcentral.com",
      "schedule": {
        "sun": "OFF",
        "mon": "09:00-18:00",
        "tue": "09:00-18:00",
        "wed": "09:00-18:00",
        "thu": "09:00-18:00",
        "fri": "09:00-18:00",
        "sat": "OFF"
      },
      "shift": "day"
    },
    "evening": {
      "name": "Lara Mae Dela Cruz",
      "email": "lara.delacruz@ringcentral.com",
      "schedule": {
        "sun": "OFF",
        "mon": "15:00-00:00",
        "tue": "15:00-00:00",
        "wed": "15:00-00:00",
        "thu": "15:00-00:00",
        "fri": "15:00-00:00",
        "sat": "OFF"
      },
      "shift": "evening"
    },
    "night": {
      "name": "Srikanth Reddy",
      "email": "srikanth.v@ringcentral.com",
      "schedule": {
        "sun": "22:30-07:30",
        "mon": "22:30-07:30",
        "tue": "22:30-07:30",
        "wed": "22:30-07:30",
        "thu": "22:30-07:30",
        "fri": "OFF",
        "sat": "OFF"
      },
      "shift": "night"
    }
  },
  "2025-11-22": {
    "early": {
      "name": "Bo Lemecha",
      "email": "Bo.Lemecha@ringcentral.com",
      "schedule": {
        "sun": "OFF",
        "mon": "06:00-14:30",
        "tue": "06:00-14:30",
        "wed": "06:00-14:30",
        "thu": "06:00-14:30",
        "fri": "06:00-14:30",
        "sat": "OFF"
      },
      "shift": "early"
    },
    "day": {
      "name": "Jeremy Rodriguez",
      "email": "jeremyr@ringcentral.com",
      "schedule": {
        "sun": "OFF",
        "mon": "08:00-16:30",
        "tue": "08:00-16:30",
        "wed": "08:00-16:30",
        "thu": "08:00-16:30",
        "fri": "08:00-16:30",
        "sat": "OFF"
      },
      "shift": "day"
    },
    "evening": {
      "name": "Lara Mae Dela Cruz",
      "email": "lara.delacruz@ringcentral.com",
      "schedule": {
        "sun": "OFF",
        "mon": "15:00-00:00",
        "tue": "15:00-00:00",
        "wed": "15:00-00:00",
        "thu": "15:00-00:00",
        "fri": "15:00-00:00",
        "sat": "OFF"
      },
      "shift": "evening"
    },
    "night": {
      "name": "Joseph Bendecio",
      "email": "joseph.bendecio@ringcentral.com",
      "schedule": {
        "sun": "OFF",
        "mon": "OFF",
        "tue": "01:00-10:00",
        "wed": "01:00-10:00",
        "thu": "01:00-10:00",
        "fri": "01:00-10:00",
        "sat": "01:00-10:00"
      },
      "shift": "night"
    }
  },
  "2025-11-23": {
    "day": {
      "name": "Eryll Azucena",
      "email": "eryll.azucena@ringcentral.com",
      "schedule": {
        "sun": "OFF",
        "mon": "08:00-15:30",
        "tue": "08:00-15:30",
        "wed": "08:00-15:30",
        "thu": "08:00-15:30",
        "fri": "08:00-15:30",
        "sat": "08:00-15:30"
      },
      "shift": "day"
    },
    "evening": {
      "name": "Love Lyn Cano",
      "email": "love.cano@ringcentral.com",
      "schedule": {
        "sun": "15:00-00:00",
        "mon": "15:00-00:00",
        "tue": "15:00-00:00",
        "wed": "15:00-00:00",
        "thu": "OFF",
        "fri": "OFF",
        "sat": "15:00-00:00"
      },
      "shift": "evening"
    },
    "night": {
      "name": "Joseph Bendecio",
      "email": "joseph.bendecio@ringcentral.com",
      "schedule": {
        "sun": "OFF",
        "mon": "OFF",
        "tue": "01:00-10:00",
        "wed": "01:00-10:00",
        "thu": "01:00-10:00",
        "fri": "01:00-10:00",
        "sat": "01:00-10:00"
      },
      "shift": "night"
    }
  },
  "2025-11-24": {
    "day": {
      "name": "Edward Salvador",
      "email": "edward.salvador@ringcentral.com",
      "schedule": {
        "sun": "08:00-15:30",
        "mon": "08:00-15:30",
        "tue": "08:00-15:30",
        "wed": "08:00-15:30",
        "thu": "08:00-15:30",
        "fri": "OFF",
        "sat": "OFF"
      },
      "shift": "day"
    },
    "evening": {
      "name": "James Belleza",
      "email": "james.belleza@ringcentral.com",
      "schedule": {
        "sun": "15:00-00:00",
        "mon": "15:00-00:00",
        "tue": "15:00-00:00",
        "wed": "15:00-00:00",
        "thu": "15:00-00:00",
        "fri": "OFF",
        "sat": "OFF"
      },
      "shift": "evening"
    },
    "night": {
      "name": "Pearce Hamblin",
      "email": "pearce.hamblin@ringcentral.com",
      "schedule": {
        "sun": "01:00-07:00",
        "mon": "01:00-07:00",
        "tue": "01:00-07:00",
        "wed": "01:00-07:00",
        "thu": "01:00-07:00",
        "fri": "OFF",
        "sat": "OFF"
      },
      "shift": "night"
    }
  },
  "2025-11-25": {
    "early": {
      "name": "Dan Baker",
      "email": "dan.baker1@ringcentral.com",
      "schedule": {
        "sun": "OFF",
        "mon": "07:00-15:00",
        "tue": "07:00-15:00",
        "wed": "07:00-15:00",
        "thu": "07:00-15:00",
        "fri": "07:00-15:00",
        "sat": "OFF"
      },
      "shift": "early"
    },
    "day": {
      "name": "John Glenn Bayron",
      "email": "john.bayron@ringcentral.com",
      "schedule": {
        "sun": "OFF",
        "mon": "08:00-15:30",
        "tue": "08:00-15:30",
        "wed": "08:00-15:30",
        "thu": "08:00-15:30",
        "fri": "08:00-15:30",
        "sat": "OFF"
      },
      "shift": "day"
    },
    "evening": {
      "name": "Lara Mae Dela Cruz",
      "email": "lara.delacruz@ringcentral.com",
      "schedule": {
        "sun": "OFF",
        "mon": "15:00-00:00",
        "tue": "15:00-00:00",
        "wed": "15:00-00:00",
        "thu": "15:00-00:00",
        "fri": "15:00-00:00",
        "sat": "OFF"
      },
      "shift": "evening"
    },
    "night": {
      "name": "Amine Dahel",
      "email": "amine.dahel@ringcentral.com",
      "schedule": {
        "sun": "00:00-06:00",
        "mon": "00:00-06:00",
        "tue": "00:00-06:00",
        "wed": "00:00-06:00",
        "thu": "00:00-06:00",
        "fri": "OFF",
        "sat": "OFF"
      },
      "shift": "night"
    }
  },
  "2025-11-26": {
    "early": {
      "name": "Nate Malone",
      "email": "nate.malone@ringcentral.com",
      "schedule": {
        "sun": "OFF",
        "mon": "07:00-16:00",
        "tue": "07:00-16:00",
        "wed": "07:00-16:00",
        "thu": "07:00-16:00",
        "fri": "07:00-16:00",
        "sat": "OFF"
      },
      "shift": "early"
    },
    "day": {
      "name": "Robert Carter",
      "email": "robert.carter@ringcentral.com",
      "schedule": {
        "sun": "OFF",
        "mon": "09:00-17:00",
        "tue": "09:00-17:00",
        "wed": "09:00-17:00",
        "thu": "09:00-17:00",
        "fri": "09:00-17:00",
        "sat": "OFF"
      },
      "shift": "day"
    },
    "evening": {
      "name": "Love Lyn Cano",
      "email": "love.cano@ringcentral.com",
      "schedule": {
        "sun": "15:00-00:00",
        "mon": "15:00-00:00",
        "tue": "15:00-00:00",
        "wed": "15:00-00:00",
        "thu": "OFF",
        "fri": "OFF",
        "sat": "15:00-00:00"
      },
      "shift": "evening"
    },
    "night": {
      "name": "Amine Dahel",
      "email": "amine.dahel@ringcentral.com",
      "schedule": {
        "sun": "00:00-06:00",
        "mon": "00:00-06:00",
        "tue": "00:00-06:00",
        "wed": "00:00-06:00",
        "thu": "00:00-06:00",
        "fri": "OFF",
        "sat": "OFF"
      },
      "shift": "night"
    }
  },
  "2025-11-27": {
    "early": {
      "name": "Peter Czarnecki",
      "email": "peter.czarnecki@ringcentral.com",
      "schedule": {
        "sun": "OFF",
        "mon": "06:00-14:30",
        "tue": "06:00-14:30",
        "wed": "06:00-14:30",
        "thu": "06:00-14:30",
        "fri": "06:00-14:30",
        "sat": "OFF"
      },
      "shift": "early"
    },
    "day": {
      "name": "John Tran",
      "email": "john.tran@ringcentral.com",
      "schedule": {
        "sun": "OFF",
        "mon": "10:00-18:00",
        "tue": "10:00-18:00",
        "wed": "10:00-18:00",
        "thu": "10:00-18:00",
        "fri": "10:00-18:00",
        "sat": "OFF"
      },
      "shift": "day"
    },
    "evening": {
      "name": "James Belleza",
      "email": "james.belleza@ringcentral.com",
      "schedule": {
        "sun": "15:00-00:00",
        "mon": "15:00-00:00",
        "tue": "15:00-00:00",
        "wed": "15:00-00:00",
        "thu": "15:00-00:00",
        "fri": "OFF",
        "sat": "OFF"
      },
      "shift": "evening"
    },
    "night": {
      "name": "Andrew Neill",
      "email": "andrew.neill@ringcentral.com",
      "schedule": {
        "sun": "03:00-09:00",
        "mon": "03:00-09:00",
        "tue": "03:00-09:00",
        "wed": "03:00-09:00",
        "thu": "03:00-09:00",
        "fri": "OFF",
        "sat": "OFF"
      },
      "shift": "night"
    }
  },
  "2025-11-28": {
    "early": {
      "name": "Cindy Hubert",
      "email": "cindy.hubert@ringcentral.com",
      "schedule": {
        "sun": "OFF",
        "mon": "07:00-16:00",
        "tue": "07:00-16:00",
        "wed": "07:00-16:00",
        "thu": "07:00-16:00",
        "fri": "07:00-16:00",
        "sat": "OFF"
      },
      "shift": "early"
    },
    "day": {
      "name": "Jared Cooper",
      "email": "jared.cooper@ringcentral.com",
      "schedule": {
        "sun": "OFF",
        "mon": "09:00-18:00",
        "tue": "09:00-18:00",
        "wed": "09:00-18:00",
        "thu": "09:00-18:00",
        "fri": "09:00-18:00",
        "sat": "OFF"
      },
      "shift": "day"
    },
    "evening": {
      "name": "James Belleza",
      "email": "james.belleza@ringcentral.com",
      "schedule": {
        "sun": "15:00-00:00",
        "mon": "15:00-00:00",
        "tue": "15:00-00:00",
        "wed": "15:00-00:00",
        "thu": "15:00-00:00",
        "fri": "OFF",
        "sat": "OFF"
      },
      "shift": "evening"
    },
    "night": {
      "name": "Andy Connolly",
      "email": "andy.connolly@ringcentral.com",
      "schedule": {
        "sun": "03:00-09:00",
        "mon": "03:00-09:00",
        "tue": "03:00-09:00",
        "wed": "03:00-09:00",
        "thu": "03:00-09:00",
        "fri": "OFF",
        "sat": "OFF"
      },
      "shift": "night"
    }
  },
  "2025-11-29": {
    "early": {
      "name": "Abby Bearden",
      "email": "abby.bearden@ringcentral.com",
      "schedule": {
        "sun": "OFF",
        "mon": "06:00-15:00",
        "tue": "06:00-15:00",
        "wed": "06:00-15:00",
        "thu": "06:00-15:00",
        "fri": "06:00-15:00",
        "sat": "OFF"
      },
      "shift": "early"
    },
    "day": {
      "name": "Mare Snyder",
      "email": "mare.snyder@ringcentral.com",
      "schedule": {
        "sun": "OFF",
        "mon": "09:00-18:00",
        "tue": "09:00-18:00",
        "wed": "09:00-18:00",
        "thu": "09:00-18:00",
        "fri": "09:00-18:00",
        "sat": "OFF"
      },
      "shift": "day"
    },
    "evening": {
      "name": "Lara Mae Dela Cruz",
      "email": "lara.delacruz@ringcentral.com",
      "schedule": {
        "sun": "OFF",
        "mon": "15:00-00:00",
        "tue": "15:00-00:00",
        "wed": "15:00-00:00",
        "thu": "15:00-00:00",
        "fri": "15:00-00:00",
        "sat": "OFF"
      },
      "shift": "evening"
    },
    "night": {
      "name": "Joseph Bendecio",
      "email": "joseph.bendecio@ringcentral.com",
      "schedule": {
        "sun": "OFF",
        "mon": "OFF",
        "tue": "01:00-10:00",
        "wed": "01:00-10:00",
        "thu": "01:00-10:00",
        "fri": "01:00-10:00",
        "sat": "01:00-10:00"
      },
      "shift": "night"
    }
  },
  "2025-11-30": {
    "day": {
      "name": "Eryll Azucena",
      "email": "eryll.azucena@ringcentral.com",
      "schedule": {
        "sun": "OFF",
        "mon": "08:00-15:30",
        "tue": "08:00-15:30",
        "wed": "08:00-15:30",
        "thu": "08:00-15:30",
        "fri": "08:00-15:30",
        "sat": "08:00-15:30"
      },
      "shift": "day"
    },
    "evening": {
      "name": "Love Lyn Cano",
      "email": "love.cano@ringcentral.com",
      "schedule": {
        "sun": "15:00-00:00",
        "mon": "15:00-00:00",
        "tue": "15:00-00:00",
        "wed": "15:00-00:00",
        "thu": "OFF",
        "fri": "OFF",
        "sat": "15:00-00:00"
      },
      "shift": "evening"
    },
    "night": {
      "name": "Joseph Bendecio",
      "email": "joseph.bendecio@ringcentral.com",
      "schedule": {
        "sun": "OFF",
        "mon": "OFF",
        "tue": "01:00-10:00",
        "wed": "01:00-10:00",
        "thu": "01:00-10:00",
        "fri": "01:00-10:00",
        "sat": "01:00-10:00"
      },
      "shift": "night"
    }
  },
  "2025-12-01": {
    "day": {
      "name": "Edward Salvador",
      "email": "edward.salvador@ringcentral.com",
      "schedule": {
        "sun": "08:00-15:30",
        "mon": "08:00-15:30",
        "tue": "08:00-15:30",
        "wed": "08:00-15:30",
        "thu": "08:00-15:30",
        "fri": "OFF",
        "sat": "OFF"
      },
      "shift": "day"
    },
    "evening": {
      "name": "Love Lyn Cano",
      "email": "love.cano@ringcentral.com",
      "schedule": {
        "sun": "15:00-00:00",
        "mon": "15:00-00:00",
        "tue": "15:00-00:00",
        "wed": "15:00-00:00",
        "thu": "OFF",
        "fri": "OFF",
        "sat": "15:00-00:00"
      },
      "shift": "evening"
    },
    "night": {
      "name": "Hugo Nickal-Thibeaud",
      "email": "hugo.thibeaud@ringcentral.com",
      "schedule": {
        "sun": "02:00-08:00",
        "mon": "02:00-08:00",
        "tue": "02:00-08:00",
        "wed": "02:00-08:00",
        "thu": "02:00-08:00",
        "fri": "OFF",
        "sat": "OFF"
      },
      "shift": "night"
    }
  },
  "2025-12-02": {
    "early": {
      "name": "Tim Arnott",
      "email": "tim.arnott@ringcentral.com",
      "schedule": {
        "sun": "OFF",
        "mon": "06:00-15:00",
        "tue": "06:00-15:00",
        "wed": "06:00-15:00",
        "thu": "06:00-15:00",
        "fri": "06:00-15:00",
        "sat": "OFF"
      },
      "shift": "early"
    },
    "day": {
      "name": "Mark Peirce",
      "email": "mark.peirce@ringcentral.com",
      "schedule": {
        "sun": "OFF",
        "mon": "09:00-18:00",
        "tue": "09:00-18:00",
        "wed": "09:00-18:00",
        "thu": "09:00-18:00",
        "fri": "09:00-18:00",
        "sat": "OFF"
      },
      "shift": "day"
    },
    "evening": {
      "name": "Love Lyn Cano",
      "email": "love.cano@ringcentral.com",
      "schedule": {
        "sun": "15:00-00:00",
        "mon": "15:00-00:00",
        "tue": "15:00-00:00",
        "wed": "15:00-00:00",
        "thu": "OFF",
        "fri": "OFF",
        "sat": "15:00-00:00"
      },
      "shift": "evening"
    },
    "night": {
      "name": "Baranee Selvendran",
      "email": "baranee.selvendran@ringcentral.com",
      "schedule": {
        "sun": "02:00-10:00",
        "mon": "02:00-10:00",
        "tue": "02:00-10:00",
        "wed": "02:00-10:00",
        "thu": "02:00-10:00",
        "fri": "OFF",
        "sat": "OFF"
      },
      "shift": "night"
    }
  },
  "2025-12-03": {
    "early": {
      "name": "Alexandra Hock",
      "email": "alexandra.hock@ringcentral.com",
      "schedule": {
        "sun": "OFF",
        "mon": "05:00-14:00",
        "tue": "05:00-14:00",
        "wed": "05:00-14:00",
        "thu": "05:00-14:00",
        "fri": "05:00-14:00",
        "sat": "OFF"
      },
      "shift": "early"
    },
    "day": {
      "name": "Roscoe Bryant",
      "email": "roscoe.bryant@ringcentral.com",
      "schedule": {
        "sun": "OFF",
        "mon": "08:30-17:00",
        "tue": "08:30-17:00",
        "wed": "08:30-17:00",
        "thu": "08:30-17:00",
        "fri": "08:30-17:00",
        "sat": "OFF"
      },
      "shift": "day"
    },
    "evening": {
      "name": "James Belleza",
      "email": "james.belleza@ringcentral.com",
      "schedule": {
        "sun": "15:00-00:00",
        "mon": "15:00-00:00",
        "tue": "15:00-00:00",
        "wed": "15:00-00:00",
        "thu": "15:00-00:00",
        "fri": "OFF",
        "sat": "OFF"
      },
      "shift": "evening"
    },
    "night": {
      "name": "Baranee Selvendran",
      "email": "baranee.selvendran@ringcentral.com",
      "schedule": {
        "sun": "02:00-10:00",
        "mon": "02:00-10:00",
        "tue": "02:00-10:00",
        "wed": "02:00-10:00",
        "thu": "02:00-10:00",
        "fri": "OFF",
        "sat": "OFF"
      },
      "shift": "night"
    }
  },
  "2025-12-04": {
    "early": {
      "name": "Marina Stambaugh",
      "email": "marina.stambaugh@ringcentral.com",
      "schedule": {
        "sun": "OFF",
        "mon": "07:00-16:00",
        "tue": "07:00-16:00",
        "wed": "07:00-16:00",
        "thu": "07:00-16:00",
        "fri": "07:00-16:00",
        "sat": "OFF"
      },
      "shift": "early"
    },
    "day": {
      "name": "Tomislav Vranjes",
      "email": "tomislav.vranjes@ringcentral.com",
      "schedule": {
        "sun": "OFF",
        "mon": "09:30-18:00",
        "tue": "09:30-18:00",
        "wed": "09:30-18:00",
        "thu": "09:30-18:00",
        "fri": "09:30-18:00",
        "sat": "OFF"
      },
      "shift": "day"
    },
    "evening": {
      "name": "Lara Mae Dela Cruz",
      "email": "lara.delacruz@ringcentral.com",
      "schedule": {
        "sun": "OFF",
        "mon": "15:00-00:00",
        "tue": "15:00-00:00",
        "wed": "15:00-00:00",
        "thu": "15:00-00:00",
        "fri": "15:00-00:00",
        "sat": "OFF"
      },
      "shift": "evening"
    },
    "night": {
      "name": "Rushikesh Sawant",
      "email": "rushikesh.sawant@ringcentral.com",
      "schedule": {
        "sun": "22:30-07:30",
        "mon": "22:30-07:30",
        "tue": "22:30-07:30",
        "wed": "22:30-07:30",
        "thu": "22:30-07:30",
        "fri": "OFF",
        "sat": "OFF"
      },
      "shift": "night"
    }
  },
  "2025-12-05": {
    "early": {
      "name": "Jenny Deasy",
      "email": "jenny.deasy@ringcentral.com",
      "schedule": {
        "sun": "OFF",
        "mon": "07:00-15:30",
        "tue": "07:00-15:30",
        "wed": "07:00-15:30",
        "thu": "07:00-15:30",
        "fri": "07:00-15:30",
        "sat": "OFF"
      },
      "shift": "early"
    },
    "day": {
      "name": "Rochelle Gobis",
      "email": "rochelle.gobis@ringcentral.com",
      "schedule": {
        "sun": "OFF",
        "mon": "08:00-15:30",
        "tue": "08:00-15:30",
        "wed": "08:00-15:30",
        "thu": "08:00-15:30",
        "fri": "08:00-15:30",
        "sat": "OFF"
      },
      "shift": "day"
    },
    "evening": {
      "name": "Lara Mae Dela Cruz",
      "email": "lara.delacruz@ringcentral.com",
      "schedule": {
        "sun": "OFF",
        "mon": "15:00-00:00",
        "tue": "15:00-00:00",
        "wed": "15:00-00:00",
        "thu": "15:00-00:00",
        "fri": "15:00-00:00",
        "sat": "OFF"
      },
      "shift": "evening"
    },
    "night": {
      "name": "Santosh Sahoo",
      "email": "santosh.sahoo@ringcentral.com",
      "schedule": {
        "sun": "22:30-07:30",
        "mon": "22:30-07:30",
        "tue": "22:30-07:30",
        "wed": "22:30-07:30",
        "thu": "22:30-07:30",
        "fri": "OFF",
        "sat": "OFF"
      },
      "shift": "night"
    }
  },
  "2025-12-06": {
    "early": {
      "name": "Bo Lemecha",
      "email": "Bo.Lemecha@ringcentral.com",
      "schedule": {
        "sun": "OFF",
        "mon": "06:00-14:30",
        "tue": "06:00-14:30",
        "wed": "06:00-14:30",
        "thu": "06:00-14:30",
        "fri": "06:00-14:30",
        "sat": "OFF"
      },
      "shift": "early"
    },
    "day": {
      "name": "Karla Talamantes",
      "email": "karla.talamantes@ringcentral.com",
      "schedule": {
        "sun": "OFF",
        "mon": "09:00-18:00",
        "tue": "09:00-18:00",
        "wed": "09:00-18:00",
        "thu": "09:00-18:00",
        "fri": "09:00-18:00",
        "sat": "OFF"
      },
      "shift": "day"
    },
    "evening": {
      "name": "Lara Mae Dela Cruz",
      "email": "lara.delacruz@ringcentral.com",
      "schedule": {
        "sun": "OFF",
        "mon": "15:00-00:00",
        "tue": "15:00-00:00",
        "wed": "15:00-00:00",
        "thu": "15:00-00:00",
        "fri": "15:00-00:00",
        "sat": "OFF"
      },
      "shift": "evening"
    },
    "night": {
      "name": "Joseph Bendecio",
      "email": "joseph.bendecio@ringcentral.com",
      "schedule": {
        "sun": "OFF",
        "mon": "OFF",
        "tue": "01:00-10:00",
        "wed": "01:00-10:00",
        "thu": "01:00-10:00",
        "fri": "01:00-10:00",
        "sat": "01:00-10:00"
      },
      "shift": "night"
    }
  },
  "2025-12-07": {
    "day": {
      "name": "Eryll Azucena",
      "email": "eryll.azucena@ringcentral.com",
      "schedule": {
        "sun": "OFF",
        "mon": "08:00-15:30",
        "tue": "08:00-15:30",
        "wed": "08:00-15:30",
        "thu": "08:00-15:30",
        "fri": "08:00-15:30",
        "sat": "08:00-15:30"
      },
      "shift": "day"
    },
    "evening": {
      "name": "Love Lyn Cano",
      "email": "love.cano@ringcentral.com",
      "schedule": {
        "sun": "15:00-00:00",
        "mon": "15:00-00:00",
        "tue": "15:00-00:00",
        "wed": "15:00-00:00",
        "thu": "OFF",
        "fri": "OFF",
        "sat": "15:00-00:00"
      },
      "shift": "evening"
    },
    "night": {
      "name": "Joseph Bendecio",
      "email": "joseph.bendecio@ringcentral.com",
      "schedule": {
        "sun": "OFF",
        "mon": "OFF",
        "tue": "01:00-10:00",
        "wed": "01:00-10:00",
        "thu": "01:00-10:00",
        "fri": "01:00-10:00",
        "sat": "01:00-10:00"
      },
      "shift": "night"
    }
  },
  "2025-12-08": {
    "day": {
      "name": "Edward Salvador",
      "email": "edward.salvador@ringcentral.com",
      "schedule": {
        "sun": "08:00-15:30",
        "mon": "08:00-15:30",
        "tue": "08:00-15:30",
        "wed": "08:00-15:30",
        "thu": "08:00-15:30",
        "fri": "OFF",
        "sat": "OFF"
      },
      "shift": "day"
    },
    "evening": {
      "name": "James Belleza",
      "email": "james.belleza@ringcentral.com",
      "schedule": {
        "sun": "15:00-00:00",
        "mon": "15:00-00:00",
        "tue": "15:00-00:00",
        "wed": "15:00-00:00",
        "thu": "15:00-00:00",
        "fri": "OFF",
        "sat": "OFF"
      },
      "shift": "evening"
    },
    "night": {
      "name": "Pearce Hamblin",
      "email": "pearce.hamblin@ringcentral.com",
      "schedule": {
        "sun": "01:00-07:00",
        "mon": "01:00-07:00",
        "tue": "01:00-07:00",
        "wed": "01:00-07:00",
        "thu": "01:00-07:00",
        "fri": "OFF",
        "sat": "OFF"
      },
      "shift": "night"
    }
  },
  "2025-12-09": {
    "early": {
      "name": "Dan Baker",
      "email": "dan.baker1@ringcentral.com",
      "schedule": {
        "sun": "OFF",
        "mon": "07:00-15:00",
        "tue": "07:00-15:00",
        "wed": "07:00-15:00",
        "thu": "07:00-15:00",
        "fri": "07:00-15:00",
        "sat": "OFF"
      },
      "shift": "early"
    },
    "day": {
      "name": "Edwin Reveley",
      "email": "edwin.reveley@ringcentral.com",
      "schedule": {
        "sun": "OFF",
        "mon": "09:30-18:00",
        "tue": "09:30-18:00",
        "wed": "09:30-18:00",
        "thu": "09:30-18:00",
        "fri": "09:30-18:00",
        "sat": "OFF"
      },
      "shift": "day"
    },
    "evening": {
      "name": "James Belleza",
      "email": "james.belleza@ringcentral.com",
      "schedule": {
        "sun": "15:00-00:00",
        "mon": "15:00-00:00",
        "tue": "15:00-00:00",
        "wed": "15:00-00:00",
        "thu": "15:00-00:00",
        "fri": "OFF",
        "sat": "OFF"
      },
      "shift": "evening"
    },
    "night": {
      "name": "Amine Dahel",
      "email": "amine.dahel@ringcentral.com",
      "schedule": {
        "sun": "00:00-06:00",
        "mon": "00:00-06:00",
        "tue": "00:00-06:00",
        "wed": "00:00-06:00",
        "thu": "00:00-06:00",
        "fri": "OFF",
        "sat": "OFF"
      },
      "shift": "night"
    }
  },
  "2025-12-10": {
    "early": {
      "name": "Nate Malone",
      "email": "nate.malone@ringcentral.com",
      "schedule": {
        "sun": "OFF",
        "mon": "07:00-16:00",
        "tue": "07:00-16:00",
        "wed": "07:00-16:00",
        "thu": "07:00-16:00",
        "fri": "07:00-16:00",
        "sat": "OFF"
      },
      "shift": "early"
    },
    "day": {
      "name": "Edward Salvador",
      "email": "edward.salvador@ringcentral.com",
      "schedule": {
        "sun": "08:00-15:30",
        "mon": "08:00-15:30",
        "tue": "08:00-15:30",
        "wed": "08:00-15:30",
        "thu": "08:00-15:30",
        "fri": "OFF",
        "sat": "OFF"
      },
      "shift": "day"
    },
    "evening": {
      "name": "Lara Mae Dela Cruz",
      "email": "lara.delacruz@ringcentral.com",
      "schedule": {
        "sun": "OFF",
        "mon": "15:00-00:00",
        "tue": "15:00-00:00",
        "wed": "15:00-00:00",
        "thu": "15:00-00:00",
        "fri": "15:00-00:00",
        "sat": "OFF"
      },
      "shift": "evening"
    },
    "night": {
      "name": "Pearce Hamblin",
      "email": "pearce.hamblin@ringcentral.com",
      "schedule": {
        "sun": "01:00-07:00",
        "mon": "01:00-07:00",
        "tue": "01:00-07:00",
        "wed": "01:00-07:00",
        "thu": "01:00-07:00",
        "fri": "OFF",
        "sat": "OFF"
      },
      "shift": "night"
    }
  },
  "2025-12-11": {
    "early": {
      "name": "Peter Czarnecki",
      "email": "peter.czarnecki@ringcentral.com",
      "schedule": {
        "sun": "OFF",
        "mon": "06:00-14:30",
        "tue": "06:00-14:30",
        "wed": "06:00-14:30",
        "thu": "06:00-14:30",
        "fri": "06:00-14:30",
        "sat": "OFF"
      },
      "shift": "early"
    },
    "day": {
      "name": "John Glenn Bayron",
      "email": "john.bayron@ringcentral.com",
      "schedule": {
        "sun": "OFF",
        "mon": "08:00-15:30",
        "tue": "08:00-15:30",
        "wed": "08:00-15:30",
        "thu": "08:00-15:30",
        "fri": "08:00-15:30",
        "sat": "OFF"
      },
      "shift": "day"
    },
    "evening": {
      "name": "Love Lyn Cano",
      "email": "love.cano@ringcentral.com",
      "schedule": {
        "sun": "15:00-00:00",
        "mon": "15:00-00:00",
        "tue": "15:00-00:00",
        "wed": "15:00-00:00",
        "thu": "OFF",
        "fri": "OFF",
        "sat": "15:00-00:00"
      },
      "shift": "evening"
    },
    "night": {
      "name": "Amine Dahel",
      "email": "amine.dahel@ringcentral.com",
      "schedule": {
        "sun": "00:00-06:00",
        "mon": "00:00-06:00",
        "tue": "00:00-06:00",
        "wed": "00:00-06:00",
        "thu": "00:00-06:00",
        "fri": "OFF",
        "sat": "OFF"
      },
      "shift": "night"
    }
  },
  "2025-12-12": {
    "early": {
      "name": "Cindy Hubert",
      "email": "cindy.hubert@ringcentral.com",
      "schedule": {
        "sun": "OFF",
        "mon": "07:00-16:00",
        "tue": "07:00-16:00",
        "wed": "07:00-16:00",
        "thu": "07:00-16:00",
        "fri": "07:00-16:00",
        "sat": "OFF"
      },
      "shift": "early"
    },
    "day": {
      "name": "Robert Carter",
      "email": "robert.carter@ringcentral.com",
      "schedule": {
        "sun": "OFF",
        "mon": "09:00-17:00",
        "tue": "09:00-17:00",
        "wed": "09:00-17:00",
        "thu": "09:00-17:00",
        "fri": "09:00-17:00",
        "sat": "OFF"
      },
      "shift": "day"
    },
    "evening": {
      "name": "James Belleza",
      "email": "james.belleza@ringcentral.com",
      "schedule": {
        "sun": "15:00-00:00",
        "mon": "15:00-00:00",
        "tue": "15:00-00:00",
        "wed": "15:00-00:00",
        "thu": "15:00-00:00",
        "fri": "OFF",
        "sat": "OFF"
      },
      "shift": "evening"
    },
    "night": {
      "name": "Andrew Neill",
      "email": "andrew.neill@ringcentral.com",
      "schedule": {
        "sun": "03:00-09:00",
        "mon": "03:00-09:00",
        "tue": "03:00-09:00",
        "wed": "03:00-09:00",
        "thu": "03:00-09:00",
        "fri": "OFF",
        "sat": "OFF"
      },
      "shift": "night"
    }
  },
  "2025-12-13": {
    "early": {
      "name": "Abby Bearden",
      "email": "abby.bearden@ringcentral.com",
      "schedule": {
        "sun": "OFF",
        "mon": "06:00-15:00",
        "tue": "06:00-15:00",
        "wed": "06:00-15:00",
        "thu": "06:00-15:00",
        "fri": "06:00-15:00",
        "sat": "OFF"
      },
      "shift": "early"
    },
    "day": {
      "name": "Eryll Azucena",
      "email": "eryll.azucena@ringcentral.com",
      "schedule": {
        "sun": "OFF",
        "mon": "08:00-15:30",
        "tue": "08:00-15:30",
        "wed": "08:00-15:30",
        "thu": "08:00-15:30",
        "fri": "08:00-15:30",
        "sat": "08:00-15:30"
      },
      "shift": "day"
    },
    "evening": {
      "name": "Lara Mae Dela Cruz",
      "email": "lara.delacruz@ringcentral.com",
      "schedule": {
        "sun": "OFF",
        "mon": "15:00-00:00",
        "tue": "15:00-00:00",
        "wed": "15:00-00:00",
        "thu": "15:00-00:00",
        "fri": "15:00-00:00",
        "sat": "OFF"
      },
      "shift": "evening"
    },
    "night": {
      "name": "Joseph Bendecio",
      "email": "joseph.bendecio@ringcentral.com",
      "schedule": {
        "sun": "OFF",
        "mon": "OFF",
        "tue": "01:00-10:00",
        "wed": "01:00-10:00",
        "thu": "01:00-10:00",
        "fri": "01:00-10:00",
        "sat": "01:00-10:00"
      },
      "shift": "night"
    }
  },
  "2025-12-14": {
    "day": {
      "name": "Eryll Azucena",
      "email": "eryll.azucena@ringcentral.com",
      "schedule": {
        "sun": "OFF",
        "mon": "08:00-15:30",
        "tue": "08:00-15:30",
        "wed": "08:00-15:30",
        "thu": "08:00-15:30",
        "fri": "08:00-15:30",
        "sat": "08:00-15:30"
      },
      "shift": "day"
    },
    "evening": {
      "name": "Love Lyn Cano",
      "email": "love.cano@ringcentral.com",
      "schedule": {
        "sun": "15:00-00:00",
        "mon": "15:00-00:00",
        "tue": "15:00-00:00",
        "wed": "15:00-00:00",
        "thu": "OFF",
        "fri": "OFF",
        "sat": "15:00-00:00"
      },
      "shift": "evening"
    },
    "night": {
      "name": "Joseph Bendecio",
      "email": "joseph.bendecio@ringcentral.com",
      "schedule": {
        "sun": "OFF",
        "mon": "OFF",
        "tue": "01:00-10:00",
        "wed": "01:00-10:00",
        "thu": "01:00-10:00",
        "fri": "01:00-10:00",
        "sat": "01:00-10:00"
      },
      "shift": "night"
    }
  },
  "2025-12-15": {
    "day": {
      "name": "Edward Salvador",
      "email": "edward.salvador@ringcentral.com",
      "schedule": {
        "sun": "08:00-15:30",
        "mon": "08:00-15:30",
        "tue": "08:00-15:30",
        "wed": "08:00-15:30",
        "thu": "08:00-15:30",
        "fri": "OFF",
        "sat": "OFF"
      },
      "shift": "day"
    },
    "evening": {
      "name": "Love Lyn Cano",
      "email": "love.cano@ringcentral.com",
      "schedule": {
        "sun": "15:00-00:00",
        "mon": "15:00-00:00",
        "tue": "15:00-00:00",
        "wed": "15:00-00:00",
        "thu": "OFF",
        "fri": "OFF",
        "sat": "15:00-00:00"
      },
      "shift": "evening"
    },
    "night": {
      "name": "Hugo Nickal-Thibeaud",
      "email": "hugo.thibeaud@ringcentral.com",
      "schedule": {
        "sun": "02:00-08:00",
        "mon": "02:00-08:00",
        "tue": "02:00-08:00",
        "wed": "02:00-08:00",
        "thu": "02:00-08:00",
        "fri": "OFF",
        "sat": "OFF"
      },
      "shift": "night"
    }
  },
  "2025-12-16": {
    "early": {
      "name": "Tim Arnott",
      "email": "tim.arnott@ringcentral.com",
      "schedule": {
        "sun": "OFF",
        "mon": "06:00-15:00",
        "tue": "06:00-15:00",
        "wed": "06:00-15:00",
        "thu": "06:00-15:00",
        "fri": "06:00-15:00",
        "sat": "OFF"
      },
      "shift": "early"
    },
    "day": {
      "name": "Mare Snyder",
      "email": "mare.snyder@ringcentral.com",
      "schedule": {
        "sun": "OFF",
        "mon": "09:00-18:00",
        "tue": "09:00-18:00",
        "wed": "09:00-18:00",
        "thu": "09:00-18:00",
        "fri": "09:00-18:00",
        "sat": "OFF"
      },
      "shift": "day"
    },
    "evening": {
      "name": "Lara Mae Dela Cruz",
      "email": "lara.delacruz@ringcentral.com",
      "schedule": {
        "sun": "OFF",
        "mon": "15:00-00:00",
        "tue": "15:00-00:00",
        "wed": "15:00-00:00",
        "thu": "15:00-00:00",
        "fri": "15:00-00:00",
        "sat": "OFF"
      },
      "shift": "evening"
    },
    "night": {
      "name": "Baranee Selvendran",
      "email": "baranee.selvendran@ringcentral.com",
      "schedule": {
        "sun": "02:00-10:00",
        "mon": "02:00-10:00",
        "tue": "02:00-10:00",
        "wed": "02:00-10:00",
        "thu": "02:00-10:00",
        "fri": "OFF",
        "sat": "OFF"
      },
      "shift": "night"
    }
  },
  "2025-12-17": {
    "early": {
      "name": "Alexandra Hock",
      "email": "alexandra.hock@ringcentral.com",
      "schedule": {
        "sun": "OFF",
        "mon": "05:00-14:00",
        "tue": "05:00-14:00",
        "wed": "05:00-14:00",
        "thu": "05:00-14:00",
        "fri": "05:00-14:00",
        "sat": "OFF"
      },
      "shift": "early"
    },
    "day": {
      "name": "Colby Jestes",
      "email": "colby.jestes@ringcentral.com",
      "schedule": {
        "sun": "OFF",
        "mon": "08:00-16:30",
        "tue": "08:00-16:30",
        "wed": "08:00-16:30",
        "thu": "08:00-16:30",
        "fri": "08:00-16:30",
        "sat": "OFF"
      },
      "shift": "day"
    },
    "evening": {
      "name": "Love Lyn Cano",
      "email": "love.cano@ringcentral.com",
      "schedule": {
        "sun": "15:00-00:00",
        "mon": "15:00-00:00",
        "tue": "15:00-00:00",
        "wed": "15:00-00:00",
        "thu": "OFF",
        "fri": "OFF",
        "sat": "15:00-00:00"
      },
      "shift": "evening"
    },
    "night": {
      "name": "Hugo Nickal-Thibeaud",
      "email": "hugo.thibeaud@ringcentral.com",
      "schedule": {
        "sun": "02:00-08:00",
        "mon": "02:00-08:00",
        "tue": "02:00-08:00",
        "wed": "02:00-08:00",
        "thu": "02:00-08:00",
        "fri": "OFF",
        "sat": "OFF"
      },
      "shift": "night"
    }
  },
  "2025-12-18": {
    "early": {
      "name": "Marina Stambaugh",
      "email": "marina.stambaugh@ringcentral.com",
      "schedule": {
        "sun": "OFF",
        "mon": "07:00-16:00",
        "tue": "07:00-16:00",
        "wed": "07:00-16:00",
        "thu": "07:00-16:00",
        "fri": "07:00-16:00",
        "sat": "OFF"
      },
      "shift": "early"
    },
    "day": {
      "name": "Mark Peirce",
      "email": "mark.peirce@ringcentral.com",
      "schedule": {
        "sun": "OFF",
        "mon": "09:00-18:00",
        "tue": "09:00-18:00",
        "wed": "09:00-18:00",
        "thu": "09:00-18:00",
        "fri": "09:00-18:00",
        "sat": "OFF"
      },
      "shift": "day"
    },
    "evening": {
      "name": "James Belleza",
      "email": "james.belleza@ringcentral.com",
      "schedule": {
        "sun": "15:00-00:00",
        "mon": "15:00-00:00",
        "tue": "15:00-00:00",
        "wed": "15:00-00:00",
        "thu": "15:00-00:00",
        "fri": "OFF",
        "sat": "OFF"
      },
      "shift": "evening"
    },
    "night": {
      "name": "Baranee Selvendran",
      "email": "baranee.selvendran@ringcentral.com",
      "schedule": {
        "sun": "02:00-10:00",
        "mon": "02:00-10:00",
        "tue": "02:00-10:00",
        "wed": "02:00-10:00",
        "thu": "02:00-10:00",
        "fri": "OFF",
        "sat": "OFF"
      },
      "shift": "night"
    }
  },
  "2025-12-19": {
    "early": {
      "name": "Jenny Deasy",
      "email": "jenny.deasy@ringcentral.com",
      "schedule": {
        "sun": "OFF",
        "mon": "07:00-15:30",
        "tue": "07:00-15:30",
        "wed": "07:00-15:30",
        "thu": "07:00-15:30",
        "fri": "07:00-15:30",
        "sat": "OFF"
      },
      "shift": "early"
    },
    "day": {
      "name": "Roscoe Bryant",
      "email": "roscoe.bryant@ringcentral.com",
      "schedule": {
        "sun": "OFF",
        "mon": "08:30-17:00",
        "tue": "08:30-17:00",
        "wed": "08:30-17:00",
        "thu": "08:30-17:00",
        "fri": "08:30-17:00",
        "sat": "OFF"
      },
      "shift": "day"
    },
    "evening": {
      "name": "Lara Mae Dela Cruz",
      "email": "lara.delacruz@ringcentral.com",
      "schedule": {
        "sun": "OFF",
        "mon": "15:00-00:00",
        "tue": "15:00-00:00",
        "wed": "15:00-00:00",
        "thu": "15:00-00:00",
        "fri": "15:00-00:00",
        "sat": "OFF"
      },
      "shift": "evening"
    },
    "night": {
      "name": "Rushikesh Sawant",
      "email": "rushikesh.sawant@ringcentral.com",
      "schedule": {
        "sun": "22:30-07:30",
        "mon": "22:30-07:30",
        "tue": "22:30-07:30",
        "wed": "22:30-07:30",
        "thu": "22:30-07:30",
        "fri": "OFF",
        "sat": "OFF"
      },
      "shift": "night"
    }
  }
}